.gitignore
CHANGELOG.rst
LICENSE.txt
MANIFEST.in
README.rst
requirements.txt
setup.py
coveralls_merge/__init__.py
coveralls_merge/core.py
coveralls_merge.egg-info/PKG-INFO
coveralls_merge.egg-info/SOURCES.txt
coveralls_merge.egg-info/dependency_links.txt
coveralls_merge.egg-info/entry_points.txt
coveralls_merge.egg-info/not-zip-safe
coveralls_merge.egg-info/requires.txt
coveralls_merge.egg-info/top_level.txt