Metadata-Version: 1.1
Name: coveralls-merge
Version: 0.0.3
Summary: Upload coverage for C extensions to coveralls.io 
Home-page: http://github.com/wiredfool/coveralls-merge
Author: Eric Soroos
Author-email: eric@soroos.net
License: MIT
Keywords: Testing,Coverage,Coveralls.io,Travis-ci.org
Platform: UNKNOWN
Classifier: Development Status :: 3 - Alpha
Classifier: Topic :: Software Development :: Testing
Classifier: Intended Audience :: Developers
Classifier: License :: OSI Approved :: MIT License
Classifier: Operating System :: OS Independent
Classifier: Programming Language :: Python
Classifier: Programming Language :: Python :: 2.6
Classifier: Programming Language :: Python :: 2.7
Classifier: Programming Language :: Python :: 3.2
Classifier: Programming Language :: Python :: 3.3
Classifier: Programming Language :: Python :: 3.4
Classifier: Programming Language :: Python :: Implementation :: PyPy
Classifier: Programming Language :: Python :: Implementation :: CPython
